DP21008UNO/Funciones.py
DP21008UNO/__init__.py
DP21008UNO-1.0.2.dist-info/METADATA
DP21008UNO-1.0.2.dist-info/WHEEL
DP21008UNO-1.0.2.dist-info/top_level.txt
DP21008UNO-1.0.2.dist-info/RECORD
