Metadata-Version: 2.1
Name: DP21008UNO
Version: 1.0.2
Summary: Librería para resolver sistemas de ecuaciones lineales con multiples metodos y ecuaciones de orden superior con biseccion
Home-page: https://github.com/dp21008/DP21008UNO.git
Author: Julio Cesar Davila Peñate
Author-email: dp21008@ues.edu.sv
License: MIT
Requires-Dist: numpy
